ms2pip/correlation.py
ms2pip/plot.py
ms2pip/constants.py
ms2pip/spectrum_input.py
ms2pip/spectrum_output.py
ms2pip/exceptions.py
ms2pip/search_space.py
ms2pip/core.py
ms2pip/__main__.py
ms2pip/spectrum.py
ms2pip/__init__.py
ms2pip/result.py
ms2pip/_cython_modules/ms2pip_pyx.pyx
ms2pip/_cython_modules/ms2pip_features_c.c
ms2pip/_cython_modules/ms2pip_init_c.c
ms2pip/_cython_modules/ms2pip_pyx.cpython-311-x86_64-linux-gnu.so
ms2pip/_cython_modules/__init__.py
ms2pip/_cython_modules/ms2pip_peaks_c.c
ms2pip/_models_c/TMT.h
ms2pip/_models_c/HCD-2019.h
ms2pip/_models_c/HCD-2019/model_20190107_HCD_train_Y.c
ms2pip/_models_c/HCD-2019/model_20190107_HCD_train_B.c
ms2pip/_models_c/HCD-2019/model_20190107_HCD_train_Y2.c
ms2pip/_models_c/HCD-2019/model_20190107_HCD_train_B2.c
ms2pip/_models_c/TMT/model_20190107_TMT_train_Y.c
ms2pip/_models_c/TMT/model_20190107_TMT_train_B.c
ms2pip/_utils/ion_mobility.py
ms2pip/_utils/xgb_models.py
ms2pip/_utils/feature_names.py
ms2pip/_utils/retention_time.py
ms2pip/_utils/cli.py
ms2pip/_utils/psm_input.py
ms2pip/_utils/encoder.py
ms2pip/_utils/dlib.py
ms2pip-4.1.1.dist-info/WHEEL
ms2pip-4.1.1.dist-info/entry_points.txt
ms2pip-4.1.1.dist-info/top_level.txt
ms2pip-4.1.1.dist-info/METADATA
ms2pip-4.1.1.dist-info/RECORD
ms2pip-4.1.1.dist-info/licenses/LICENSE
