Metadata-Version: 2.4
Name: ms2pip
Version: 4.1.1
Summary: MS2PIP: Accurate and versatile peptide fragmentation spectrum prediction.
Author: Sven Degroeve, Ana Sílvia C. Silva
Author-email: Ralf Gabriels <ralf@gabriels.dev>, Arthur Declercq <arthur.declercq@ugent.be>, Kevin Velghe <kevin.velghe@ugent.be>
License:                                  Apache License
Project-URL: documentation, http://compomics.github.io/projects/ms2pip
Project-URL: source, https://github.com/compomics/ms2pip
Project-URL: tracker, https://github.com/compomics/ms2pip/issues
Project-URL: webserver, https://iomics.ugent.be/ms2pip/
Project-URL: publication, https://doi.org/10.1093/nar/gkad335/
Keywords: MS2PIP,proteomics,peptide fragmentation,peak intensity prediction,spectrum prediction,machine learning,spectral library,fasta2speclib
Classifier: Intended Audience :: Science/Research
Classifier: License :: OSI Approved :: Apache Software License
Classifier: Operating System :: POSIX :: Linux
Classifier: Operating System :: MacOS :: MacOS X
Classifier: Operating System :: Microsoft :: Windows
Classifier: Programming Language :: Python :: 3 :: Only
Classifier: Topic :: Scientific/Engineering :: Bio-Informatics
Classifier: Development Status :: 5 - Production/Stable
Requires-Python: >=3.9
License-File: LICENSE
Requires-Dist: numpy<3,>=1.25
Requires-Dist: pandas<3,>=1
Requires-Dist: pyarrow
Requires-Dist: pyteomics<5,>=3.5
Requires-Dist: sqlalchemy<3,>=1.4
Requires-Dist: click<9,>=7
Requires-Dist: xgboost<3,>=1.3
Requires-Dist: lxml>=4
Requires-Dist: rich>=13
Requires-Dist: pydantic>=2
Requires-Dist: werkzeug>=2
Requires-Dist: psm_utils>=1.0
Requires-Dist: ms2rescore-rs<2,>=0.4
Provides-Extra: plotting
Requires-Dist: matplotlib>=3.0; extra == "plotting"
Requires-Dist: spectrum-utils>=0.4; extra == "plotting"
Provides-Extra: dev
Requires-Dist: black; extra == "dev"
Requires-Dist: isort>5; extra == "dev"
Requires-Dist: pytest; extra == "dev"
Provides-Extra: docs
Requires-Dist: sphinx; extra == "docs"
Requires-Dist: numpydoc<2,>=1; extra == "docs"
Requires-Dist: recommonmark; extra == "docs"
Requires-Dist: toml; extra == "docs"
Requires-Dist: semver>=2; extra == "docs"
Requires-Dist: sphinx_rtd_theme; extra == "docs"
Requires-Dist: sphinx-autobuild; extra == "docs"
Requires-Dist: sphinx-automodapi; extra == "docs"
Requires-Dist: sphinx-click; extra == "docs"
Dynamic: license-file
